leilapdf/__init__.py
leilapdf/pdf2image.py
leilapdf/pdf2text.py
leilapdf-0.0.1.dist-info/LICENSE
leilapdf-0.0.1.dist-info/METADATA
leilapdf-0.0.1.dist-info/WHEEL
leilapdf-0.0.1.dist-info/top_level.txt
leilapdf-0.0.1.dist-info/RECORD
