Metadata-Version: 2.1
Name: leilapdf
Version: 0.0.1
Summary: A Python package to convert PDFs to text
License-File: LICENSE
